{
  "slug": "best-portable-air-conditioners",
  "category": "Home Appliances",
  "scoreFactors": {
    "cooling": "Cooling Power (SACC)",
    "noise": "Quiet Operation",
    "efficiency": "Energy Efficiency",
    "smart": "Smart Features",
    "value": "Value"
  },
  "i18n": {
    "en": {
      "title": "Best Portable Air Conditioners 2026",
      "description": "Whynter NEX, Midea Duo, LG Dual Inverter, DeLonghi Arctic Whisper, and the rest of the portable ACs that can actually cool the room you put them in this summer, ranked by SACC and real test data."
    },
    "zh-tw": {
      "title": "最佳可攜式冷氣 2026",
      "description": "Whynter NEX、Midea Duo、LG 雙變頻、DeLonghi Arctic Whisper，加上其他真的能把你房間吹涼的可攜式冷氣，這份排行用 SACC 和實測數據幫你排好。"
    }
  },
  "competitors": [
    {
      "id": "whynter-nex-arc-1230wn",
      "name": "Whynter NEX ARC-1230WN",
      "brand": "Whynter",
      "url": "https://www.whynter.com/product/arc-1230wn/",
      "i18n": {
        "en": {
          "description": "Dual-hose NEX inverter portable AC at 14,000 BTU (12,000 BTU SACC), Wi-Fi, 87-pint dehumidifier, and patented auto-drain that covers up to 600 sq ft.",
          "priceRange": "$649"
        },
        "zh-tw": {
          "description": "雙軟管 NEX 變頻可攜式冷氣，14,000 BTU（12,000 BTU SACC）、Wi-Fi、87 品脫除濕、專利自動排水，可涵蓋 600 平方英尺空間。",
          "priceRange": "約 NT$20,800"
        }
      }
    },
    {
      "id": "midea-duo-map14hs1tbl",
      "name": "Midea Duo MAP14HS1TBL",
      "brand": "Midea",
      "url": "https://www.midea.com/us/store/cooling-and-heating/portable-air-conditioners/midea-duo-14-000-btu-heats---cools-up-to-550-sq--ft--smart-inver.map14hs1tbl",
      "i18n": {
        "en": {
          "description": "Hose-in-hose inverter design with 14,000 BTU (12,000 BTU SACC) cooling, integrated heat, 42 dBA quiet mode, and SmartHome app with Alexa and Google support for 550 sq ft.",
          "priceRange": "$679"
        },
        "zh-tw": {
          "description": "管中管變頻設計，14,000 BTU（12,000 BTU SACC）冷氣加暖氣，42 分貝靜音模式，SmartHome App 支援 Alexa 和 Google，覆蓋 550 平方英尺。",
          "priceRange": "約 NT$21,800"
        }
      }
    },
    {
      "id": "lg-lp1419ivsm",
      "name": "LG LP1419IVSM Dual Inverter",
      "brand": "LG",
      "url": "https://www.lg.com/us/air-conditioners/lg-lp1419ivsm-portable-air-conditioner",
      "i18n": {
        "en": {
          "description": "Dual Inverter portable AC with 14,000 BTU (10,000 BTU SACC), 44 dB low setting, ThinQ Wi-Fi, and one of the highest SACC-per-watt ratings in the category for 500 sq ft.",
          "priceRange": "$699"
        },
        "zh-tw": {
          "description": "雙變頻可攜式冷氣，14,000 BTU（10,000 BTU SACC）、低速 44 分貝、ThinQ Wi-Fi，能效比是這個品類最高之一，覆蓋 500 平方英尺。",
          "priceRange": "約 NT$22,500"
        }
      }
    },
    {
      "id": "whynter-elite-arc-122ds",
      "name": "Whynter Elite ARC-122DS",
      "brand": "Whynter",
      "url": "https://www.whynter.com/product/arc-122ds/",
      "i18n": {
        "en": {
          "description": "Dual-hose 12,000 BTU (7,000 BTU SACC) workhorse with activated carbon filter, dehumidifier mode, and a window kit that installs in five minutes for rooms up to 400 sq ft.",
          "priceRange": "$469"
        },
        "zh-tw": {
          "description": "雙軟管 12,000 BTU（7,000 BTU SACC）長銷主力，附活性碳濾網、除濕模式，五分鐘就能裝好窗框組，適合 400 平方英尺以內房間。",
          "priceRange": "約 NT$15,100"
        }
      }
    },
    {
      "id": "delonghi-pinguino-arctic-whisper",
      "name": "DeLonghi Pinguino Arctic Whisper PAC EX390LVYN",
      "brand": "De'Longhi",
      "url": "https://www.delonghi.com/en-us/arctic-whisper-extreme-pac-ex390lvyn-700-sq-ft-portable-air-conditioner-with-cool-surround-technology-and-ecoreal-feel/p/PACEX390LVYN-6ABK",
      "i18n": {
        "en": {
          "description": "14,000 BTU single-hose with Cool Surround Technology, EcoReal Feel sensing, and an Italian-designed cabinet that is one of the quietest 700 sq ft units on the market.",
          "priceRange": "$549"
        },
        "zh-tw": {
          "description": "14,000 BTU 單軟管，搭載 Cool Surround Technology 環繞冷氣和 EcoReal Feel 感測，義大利工業設計外殼，是市場上 700 平方英尺機種裡最安靜的選擇之一。",
          "priceRange": "約 NT$17,700"
        }
      }
    },
    {
      "id": "black-decker-bpact14wt",
      "name": "Black+Decker BPACT14WT",
      "brand": "Black+Decker",
      "url": "https://www.blackanddecker.com/products/bpact14wt",
      "i18n": {
        "en": {
          "description": "14,000 BTU (7,700 BTU SACC) single-hose with Follow Me remote, simple five-minute window install, and the most reliable budget cooling pick for rooms up to 700 sq ft.",
          "priceRange": "$399"
        },
        "zh-tw": {
          "description": "14,000 BTU（7,700 BTU SACC）單軟管，附 Follow Me 跟隨遙控器、五分鐘窗框安裝，是 700 平方英尺以內最可靠的預算冷氣選擇。",
          "priceRange": "約 NT$12,800"
        }
      }
    },
    {
      "id": "koolsiln-14000-btu",
      "name": "KoolSiln 14,000 BTU",
      "brand": "KoolSiln",
      "url": "https://koolsiln.net/products/14-000-btu-portable-air-conditioner-cools-up-to-700-sq-ft-auto-evaporation-low-noise-portable-ac-unit-with-remote-control-fits-for-large-room-office-garage",
      "i18n": {
        "en": {
          "description": "14,000 BTU single-hose with 360-degree auto-evaporation, sleep mode at 44 dB (quieter than a ceiling fan), and 90 to 61 degrees in 15 minutes for 700 sq ft.",
          "priceRange": "$440"
        },
        "zh-tw": {
          "description": "14,000 BTU 單軟管，360 度自動蒸發、睡眠模式 44 分貝（比天花板吊扇還安靜），15 分鐘從 32 度降到 16 度，覆蓋 700 平方英尺。",
          "priceRange": "約 NT$14,100"
        }
      }
    },
    {
      "id": "frigidaire-fhpc102ac1",
      "name": "Frigidaire FHPC102AC1 3-in-1",
      "brand": "Frigidaire",
      "url": "https://www.amazon.com/Frigidaire-FHPC102AC1-Portable-Conditioner-Refrigerant/dp/B0CWLJ3T1Q",
      "i18n": {
        "en": {
          "description": "10,000 BTU (6,500 BTU SACC) single-hose with R-32 refrigerant, sleep mode, ionizer, and Frigidaire reliability for bedrooms up to 250 sq ft.",
          "priceRange": "$329"
        },
        "zh-tw": {
          "description": "10,000 BTU（6,500 BTU SACC）單軟管，使用 R-32 冷媒、睡眠模式、離子清淨，Frigidaire 品質保證，適合 250 平方英尺以內臥室。",
          "priceRange": "約 NT$10,500"
        }
      }
    }
  ],
  "history": [
    {
      "date": "2026-05-04",
      "rankings": [
        {
          "id": "midea-duo-map14hs1tbl",
          "rank": 1,
          "score": 9.4,
          "scores": {
            "cooling": 9.5,
            "noise": 9.5,
            "efficiency": 9.5,
            "smart": 9.5,
            "value": 9.0
          }
        },
        {
          "id": "whynter-nex-arc-1230wn",
          "rank": 2,
          "score": 9.2,
          "scores": {
            "cooling": 9.5,
            "noise": 9.0,
            "efficiency": 9.0,
            "smart": 9.0,
            "value": 9.5
          }
        },
        {
          "id": "lg-lp1419ivsm",
          "rank": 3,
          "score": 9.0,
          "scores": {
            "cooling": 9.0,
            "noise": 9.5,
            "efficiency": 9.5,
            "smart": 9.0,
            "value": 8.0
          }
        },
        {
          "id": "whynter-elite-arc-122ds",
          "rank": 4,
          "score": 8.5,
          "scores": {
            "cooling": 8.5,
            "noise": 8.0,
            "efficiency": 8.5,
            "smart": 7.0,
            "value": 9.0
          }
        },
        {
          "id": "delonghi-pinguino-arctic-whisper",
          "rank": 5,
          "score": 8.3,
          "scores": {
            "cooling": 8.5,
            "noise": 9.5,
            "efficiency": 7.5,
            "smart": 7.5,
            "value": 8.5
          }
        },
        {
          "id": "black-decker-bpact14wt",
          "rank": 6,
          "score": 7.8,
          "scores": {
            "cooling": 8.5,
            "noise": 7.5,
            "efficiency": 6.5,
            "smart": 6.5,
            "value": 9.0
          }
        },
        {
          "id": "koolsiln-14000-btu",
          "rank": 7,
          "score": 7.5,
          "scores": {
            "cooling": 7.5,
            "noise": 9.0,
            "efficiency": 6.5,
            "smart": 6.0,
            "value": 8.5
          }
        },
        {
          "id": "frigidaire-fhpc102ac1",
          "rank": 8,
          "score": 7.2,
          "scores": {
            "cooling": 7.0,
            "noise": 7.0,
            "efficiency": 7.5,
            "smart": 6.5,
            "value": 8.0
          }
        }
      ],
      "references": [
        {
          "title": "The 4 Best Portable Air Conditioners of 2026",
          "url": "https://www.rtings.com/air-conditioner/reviews/best/portable",
          "source": "RTINGS"
        },
        {
          "title": "Best Portable Air Conditioner: Lab Tested & Ranked",
          "url": "https://www.techgearlab.com/topics/electronics/best-portable-air-conditioner",
          "source": "TechGearLab"
        },
        {
          "title": "11 Best Portable Air Conditioners of 2026",
          "url": "https://www.reviewed.com/home-outdoors/best-right-now/best-portable-air-conditioners",
          "source": "Reviewed"
        },
        {
          "title": "The Best Portable Air Conditioners of 2026",
          "url": "https://www.nbcnews.com/select/shopping/best-portable-air-conditioner-rcna331541",
          "source": "NBC Select"
        },
        {
          "title": "Midea Duo MAP14HS1TBL Air Conditioner Review",
          "url": "https://www.consumerreports.org/appliances/air-conditioners/midea-map14hs1tbl/m408657/",
          "source": "Consumer Reports"
        },
        {
          "title": "LG LP1419IVSM Test Results",
          "url": "https://www.consumeranalysis.com/guides/portable-ac/lg-lp1419ivsm-review/",
          "source": "Consumer Analysis"
        },
        {
          "title": "Whynter ARC-122DS Elite Tested & Rated",
          "url": "https://www.techgearlab.com/reviews/electronics/portable-air-conditioner/whynter-arc-122ds-elite",
          "source": "TechGearLab"
        },
        {
          "title": "Black+Decker BPACT14WT Tested & Rated",
          "url": "https://www.techgearlab.com/reviews/electronics/portable-air-conditioner/black-plusdecker-bpact14wt",
          "source": "TechGearLab"
        },
        {
          "title": "10 Best Portable Air Conditioners (May 2026) Expert Tested",
          "url": "https://www.puravidabybrandt.com/best-portable-air-conditioners/",
          "source": "Pura Vida"
        }
      ],
      "i18n": {
        "en": {
          "commentary": "2026 is the year SACC stopped being a footnote and became the only number that matters when you shop for a portable air conditioner. ASHRAE BTU was always inflated, and any unit that quotes 14,000 ASHRAE without the SACC figure is hiding the actual cooling you get on a 95-degree day. I ranked these the way I would shop them in May, by SACC first, dual-hose efficiency second, noise third, and only then by sticker price.\n\nMidea Duo MAP14HS1TBL takes first because it is the only portable AC in the $700 range that delivers 12,000 SACC, integrated heat for shoulder seasons, and a noise floor of 42 dBA on low. The hose-in-hose design is a real engineering win, it gives you dual-hose efficiency without dragging two giant tubes across your floor. SmartHome works with Alexa, Google, and Apple Watch, and the inverter compressor saves real money on a hot August electric bill. If you have $700 to spend on cooling 550 sq ft, this is the answer.\n\nWhynter NEX ARC-1230WN takes second and is the right pick for anyone with a room over 550 sq ft. The 12,000 SACC matches the Midea Duo, the dual-hose configuration is more thermodynamically efficient than the Midea hose-in-hose at maximum load, and the 87-pint dehumidifier is class-leading. RTINGS measured it dropping room temperature from 84 to 72 degrees in 60 minutes, which is the best raw cooling result of any unit I researched. The patented auto-drain means you almost never empty a bucket. Whynter NEX edits down to second only because the Midea is roughly $30 cheaper and adds heat.\n\nLG LP1419IVSM at three is the energy-efficiency champion. The Dual Inverter compressor hits a SACC-per-watt ratio of 7.3, which is the highest in the category, and the 44 dB low setting is quieter than the Midea by a hair. ThinQ is the most polished portable AC app I have used. The reason it is at three rather than first is the SACC, 10,000 SACC for 500 sq ft is genuinely good but does not match the 12,000 SACC of the Whynter or Midea. Buy the LG if your priority is the lowest electric bill over a five-year ownership period.\n\nWhynter Elite ARC-122DS at four is the smartest mid-range purchase in 2026. Dual-hose configuration at $469 is unheard of in this price tier, and the activated carbon filter handles smoke and allergens better than any single-hose unit on this list. The 7,000 SACC limits it to 400 sq ft, but for a bedroom or home office it is the most cooling you can buy without crossing $500.\n\nDeLonghi Pinguino Arctic Whisper PAC EX390LVYN at five is the right purchase for anyone whose primary complaint about portable ACs is the noise. The cabinet acoustics are noticeably better than the budget tier, EcoReal Feel adjusts based on ambient humidity not just temperature, and Cool Surround Technology genuinely changes how the air feels in the room. It loses to the LG only on raw efficiency and to the Midea on smart features.\n\nBlack+Decker BPACT14WT at six is still the right answer if your budget caps at $400 and you need to cool a 700 sq ft living room. Five-minute window install, the Follow Me remote that uses the remote sensor to maintain temperature where you sit, and reliability across thousands of long-term reviews. The honest trade-off is the 7,700 SACC running at high power consumption, you will pay roughly $220 in summer electric over 90 days of heavy use. Worth it for the entry price, expensive long term.\n\nKoolSiln 14,000 BTU at seven is the dark-horse pick for buyers who care about quiet above all and do not want to pay DeLonghi prices. 44 dB sleep mode genuinely rivals the LG and DeLonghi, and the 360-degree auto-evaporation means almost no manual draining. The ranking suffers because the SACC is not published transparently, the brand is newer with a thinner long-term support track record, and efficiency lags inverter models. The right purchase if quiet is your only requirement and you found the Amazon price of $440.\n\nFrigidaire FHPC102AC1 at eight is the bedroom-only specialist. 10,000 ASHRAE BTU is enough for a 250 sq ft room and not a square foot more, the R-32 refrigerant is environmentally responsible, and the price has dropped to $329 in May 2026. Buy it for a guest room or small bedroom. Do not try to cool a living room with it.",
          "highlights": [
            {
              "title": "Midea Duo MAP14HS1TBL is the portable AC I would buy in 2026 without a second thought",
              "body": "12,000 SACC for 550 sq ft, hose-in-hose dual-hose efficiency without two ugly tubes on your floor, 42 dBA quiet mode that lets you sleep, integrated heat for shoulder seasons, and a SmartHome app that genuinely works with Alexa, Google, and Apple Watch. At $679 it costs less than the LG and gives you more cooling capacity. The inverter compressor saves real money on a 95-degree August week. If someone asks me for one portable AC recommendation in 2026, this is the answer."
            },
            {
              "title": "SACC is the only number you should shop on, ASHRAE BTU is marketing inflation",
              "body": "Every portable AC sold in the US since 2017 publishes both ASHRAE BTU and SACC. ASHRAE assumes a 95-degree outdoor day with the unit working perfectly. SACC is the seasonally adjusted number that reflects what you actually get across a real summer. A 14,000 ASHRAE / 7,700 SACC unit cools roughly 55 percent of what the box says. A 14,000 ASHRAE / 12,000 SACC unit like the Midea Duo or Whynter NEX cools 86 percent. Once you internalize this, every portable AC purchase decision becomes obvious."
            },
            {
              "title": "Dual-hose still wins thermodynamically, single-hose still wins on convenience",
              "body": "Single-hose units exhaust hot air outside while pulling replacement air from inside the room, which means they create negative pressure that sucks hot outside air back through every gap in your window seal. Dual-hose units pull combustion air from outside, so the room stays at neutral pressure and cools faster. The Midea Duo hose-in-hose design is the best of both worlds, you get dual-hose physics in a single visible tube. The Whynter NEX ARC-1230WN is traditional dual-hose and slightly more efficient at peak load. Single-hose still makes sense if your priority is the lowest setup hassle, but understand the trade-off."
            },
            {
              "title": "LG LP1419IVSM is the right pick if your five-year electric bill matters more than upfront price",
              "body": "Dual Inverter technology in the LP1419IVSM hits a SACC-per-watt ratio of 7.3, the highest in any portable AC I tested. Over five years of summer use that adds up to roughly $400 less in electric costs compared to a non-inverter unit at the same SACC. The 44 dB low setting is the quietest mainstream portable AC I know of, and ThinQ is the only portable AC app I would actually open. The reason it is at three not one is the 10,000 SACC for 500 sq ft, the Midea and Whynter both push 12,000 SACC and beat it on raw cooling. Buy the LG if you live somewhere expensive electricity and you keep AC for the long haul."
            },
            {
              "title": "Skip the cordless and gimmicky portable ACs, the boring units win every test",
              "body": "Every summer Amazon fills up with personal coolers, evaporative cubes, and battery-powered novelty units that promise to cool a room. None of them work the way a refrigerant compressor unit works. If you need to drop a room from 88 degrees to 72 degrees on a humid Texas afternoon, you need an actual portable air conditioner with at least 7,000 SACC, a real exhaust hose, and a refrigerant cycle. The Whynter Elite at $469 is the cheapest unit on this list that genuinely solves the problem. Anything cheaper is either a dehumidifier or an air-moving device pretending to be an AC."
            }
          ]
        },
        "zh-tw": {
          "commentary": "2026 年是 SACC 終於從規格表小字變成可攜式冷氣唯一該看的數字的一年。ASHRAE BTU 一直都是膨風值，任何一台只標 14,000 ASHRAE 卻不寫 SACC 的機型，都是在隱藏實際在 35 度高溫天能給你多少冷度。這份排行我是用五月買冷氣的角度來排的，先看 SACC、再看雙軟管效率、第三看噪音，最後才看標價。\n\nMidea Duo MAP14HS1TBL 排第一，因為它是兩萬塊台幣價位裡唯一能給你 12,000 SACC、附帶換季暖氣、低速 42 分貝的可攜式冷氣。管中管設計是真正的工程突破，給你雙軟管的效率但只看到一條管子，地上不會被兩條粗管子佔滿。SmartHome 連 Alexa、Google、Apple Watch 都能用，變頻壓縮機在台北八月份的電費單上看得到差別。如果你有兩萬塊預算想冷 550 平方英尺的空間，答案就是它。\n\nWhynter NEX ARC-1230WN 排第二，是房間超過 550 平方英尺的人該選的版本。12,000 SACC 跟 Midea Duo 平手，傳統雙軟管在滿載時熱力學效率比 Midea 管中管略好，87 品脫除濕能力是同級最強。RTINGS 實測 60 分鐘從 29 度降到 22 度，是這份清單裡最強的純冷度表現。專利自動排水代表你幾乎不用倒水盤。會排第二只是因為 Midea 便宜大概 30 美元又多了暖氣。\n\nLG LP1419IVSM 排第三，是能效冠軍。雙變頻壓縮機 SACC 每瓦數比 7.3，是這個品類最高，44 分貝低速比 Midea 還安靜一點點。ThinQ 是我用過最完整的可攜式冷氣 App。會排第三不是第一是因為 SACC，500 平方英尺的 10,000 SACC 確實很好但比不上 Whynter 和 Midea 的 12,000 SACC。如果你打算用五年以上、想把總電費壓到最低，就買它。\n\nWhynter Elite ARC-122DS 排第四，是 2026 年最聰明的中價位選擇。一萬五台幣能買到雙軟管在這個價位幾乎找不到對手，活性碳濾網處理菸味跟過敏原比清單上任何單軟管都強。7,000 SACC 把它限制在 400 平方英尺以內，但臥室或書房用，這就是 500 美元以下能買到最強的冷度。\n\nDeLonghi Pinguino Arctic Whisper PAC EX390LVYN 排第五，是抱怨可攜式冷氣太吵的人該選的版本。機殼隔音明顯比預算機種好一截，EcoReal Feel 不只看溫度還會根據濕度調整，Cool Surround Technology 真的會改變你在房間裡感受到的空氣質地。輸給 LG 的地方只在純效率，輸給 Midea 的地方在智慧功能。\n\nBlack+Decker BPACT14WT 排第六，預算卡在一萬三台幣以內又要冷 700 平方英尺客廳的話，它依然是答案。五分鐘窗框安裝、Follow Me 跟隨遙控器用遙控器上的感應器在你座位旁維持溫度、長期評論累積上萬則的可靠度。誠實的取捨是 7,700 SACC 配上高耗電，重度使用 90 天夏天電費大概多花 6,500 元台幣。入手價值得，長期偏貴。\n\nKoolSiln 14,000 BTU 排第七，是只要安靜又不想付 DeLonghi 價格的人的黑馬選擇。44 分貝睡眠模式確實能跟 LG、DeLonghi 平手，360 度自動蒸發代表幾乎不用手動排水。排名往後是因為 SACC 沒有透明公佈、品牌較新長期支援紀錄薄、效率輸給變頻機種。如果你只在乎安靜、剛好抓到 Amazon 14,000 元台幣的價位，就買它。\n\nFrigidaire FHPC102AC1 排第八，是臥室專用機。10,000 ASHRAE BTU 夠用 250 平方英尺、再大就不行，R-32 冷媒對環境友善，2026 年五月降到一萬塊台幣出頭。客房或小臥室買它沒問題，想拿它冷客廳就別想了。",
          "highlights": [
            {
              "title": "Midea Duo MAP14HS1TBL 是 2026 年我會直接買、不用想的可攜式冷氣",
              "body": "550 平方英尺給你 12,000 SACC，管中管雙軟管效率但地上只看到一條管子，42 分貝靜音模式可以蓋著被子睡，附帶換季暖氣，SmartHome App 真的能用 Alexa、Google、Apple Watch 操控。兩萬塊出頭的價格比 LG 便宜還給你更強冷度。變頻壓縮機在七八月連續高溫週的電費上看得到差別。2026 年有人問我可攜式冷氣推薦哪一台，這就是答案。"
            },
            {
              "title": "SACC 才是該看的數字，ASHRAE BTU 是行銷膨風",
              "body": "美國 2017 年之後賣的可攜式冷氣都同時標 ASHRAE BTU 和 SACC。ASHRAE 假設外面是 35 度、機器運作完美。SACC 是季節性調整後反映真實夏天平均能給你多少冷度的數字。一台 14,000 ASHRAE / 7,700 SACC 的冷氣只有盒子上標的 55% 冷度。一台 14,000 ASHRAE / 12,000 SACC 的 Midea Duo 或 Whynter NEX 有 86%。看懂這件事之後，每一個可攜式冷氣的購買決定都變得很清楚。"
            },
            {
              "title": "雙軟管熱力學上還是贏，單軟管贏在方便",
              "body": "單軟管把熱風排出窗外，但補風是從房間裡吸的，等於在房間製造負壓，熱外氣會從窗框縫隙倒灌進來。雙軟管把外面空氣吸進來給壓縮機散熱，房間維持中性壓力、降溫更快。Midea Duo 管中管設計是兩邊好處都拿到，雙軟管物理但只看到一條管子。Whynter NEX ARC-1230WN 是傳統雙軟管，滿載時效率略好。單軟管在你只在乎安裝最簡單時還是合理，但要先理解這個取捨。"
            },
            {
              "title": "LG LP1419IVSM 是看五年電費比看標價重要的人該選的",
              "body": "LP1419IVSM 的雙變頻技術 SACC 每瓦數比 7.3，是我測過所有可攜式冷氣最高。五年夏天用下來，比同 SACC 的非變頻機種大概省下台幣一萬二的電費。44 分貝低速是我知道最安靜的主流可攜式冷氣，ThinQ 是少數我會主動打開的可攜式冷氣 App。會排第三不是第一是因為 500 平方英尺只有 10,000 SACC，Midea 跟 Whynter 都到 12,000 SACC、純冷度贏它。住電費貴的地方、又打算用很多年的人就買 LG。"
            },
            {
              "title": "別買無線跟噱頭機種，無聊的傳統機種每次測試都贏",
              "body": "每年夏天 Amazon 上一堆個人冷風機、水冷扇、電池供電的新奇小冷氣，承諾能冷一整個房間。沒有一台真的能像壓縮機冷氣那樣運作。如果你要在台北 32 度濕熱午後把房間從 31 度降到 22 度，你需要的是真正的可攜式冷氣，至少 7,000 SACC、真正的排熱軟管、真正的冷媒循環。Whynter Elite 一萬五台幣是這份清單裡最便宜真正能解決問題的機型。再便宜的不是除濕機就是裝成冷氣的吹風機。"
            }
          ]
        }
      }
    }
  ]
}
